{"version":3,"kind":"Article","sha256":"39e62626fbd297a4278de3e1562f2ea6c9ad089395abec7cfe0b652a00769dd4","slug":"start-here","location":"/site/start-here.md","dependencies":[],"frontmatter":{"title":"Start Here","description":"A guided learning path through LS100, for self-paced learners and enrolled students alike.","short_title":"Start Here","open_access":true,"license":{"content":{"id":"CC-BY-NC-4.0","url":"https://creativecommons.org/licenses/by-nc/4.0/","name":"Creative Commons Attribution Non Commercial 4.0 International","CC":true}},"github":"https://github.com/Souvik-Mandal-Harvard/Computational-Behavioral-Sciences_LS100_Harvard","source_url":"https://github.com/Souvik-Mandal-Harvard/Computational-Behavioral-Sciences_LS100_Harvard/blob/main/site/start-here.md","edit_url":"https://github.com/Souvik-Mandal-Harvard/Computational-Behavioral-Sciences_LS100_Harvard/edit/main/site/start-here.md","thumbnail":"/teaching-learning/ls100/build/LS100_Learning-Path_-5280ce1dc304ac663ed9ee9685114715.png","exports":[{"format":"md","filename":"start-here.md","url":"/teaching-learning/ls100/build/start-here-d643f5b2e413564a7303d1b8c1b9bab8.md"}]},"mdast":{"type":"root","children":[{"type":"block","children":[{"type":"paragraph","position":{"start":{"line":7,"column":1},"end":{"line":9,"column":1}},"children":[{"type":"text","value":"Every project in LS100 follows the same arc — frame a question, learn the tools, collect data,\nanalyze it, and communicate the result. This page maps the whole route; you’ll only ever focus\non your next step.","position":{"start":{"line":7,"column":1},"end":{"line":7,"column":1}},"key":"P7WMGySkUz"}],"key":"fmz6n7MlYu"},{"type":"image","url":"/teaching-learning/ls100/build/LS100_Learning-Path_-5280ce1dc304ac663ed9ee9685114715.png","alt":"The LS100 research learning path","position":{"start":{"line":11,"column":1},"end":{"line":11,"column":1}},"key":"U370mp1xqo","urlSource":"_static/LS100_Learning-Path_Roadmap.png"},{"type":"heading","depth":2,"position":{"start":{"line":13,"column":1},"end":{"line":13,"column":1}},"children":[{"type":"text","value":"Jump to your starting point","position":{"start":{"line":13,"column":1},"end":{"line":13,"column":1}},"key":"isC74E3c0R"}],"identifier":"jump-to-your-starting-point","label":"Jump to your starting point","html_id":"jump-to-your-starting-point","implicit":true,"key":"nuLIxgjPqD"},{"type":"list","ordered":false,"spread":false,"position":{"start":{"line":15,"column":1},"end":{"line":20,"column":1}},"children":[{"type":"listItem","spread":true,"position":{"start":{"line":15,"column":1},"end":{"line":15,"column":1}},"children":[{"type":"paragraph","children":[{"type":"strong","position":{"start":{"line":15,"column":1},"end":{"line":15,"column":1}},"children":[{"type":"text","value":"I’m new to coding","position":{"start":{"line":15,"column":1},"end":{"line":15,"column":1}},"key":"XRDb1zeMsT"}],"key":"euY3CpPpaN"},{"type":"text","value":" → start with ","position":{"start":{"line":15,"column":1},"end":{"line":15,"column":1}},"key":"Zt7CgZZ6g6"},{"type":"link","url":"/module-00b-python-fundamentals","position":{"start":{"line":15,"column":1},"end":{"line":15,"column":1}},"children":[{"type":"text","value":"Module 00B · Python Fundamentals","position":{"start":{"line":15,"column":1},"end":{"line":15,"column":1}},"key":"e3UJGr9GdY"}],"urlSource":"../LS100_00B_Python-Fundamentals/Module-00B_Python-Fundamentals.md","dataUrl":"/module-00b-python-fundamentals.json","internal":true,"protocol":"file","key":"KY7jCtR8cr"},{"type":"text","value":", Notebook 01.","position":{"start":{"line":15,"column":1},"end":{"line":15,"column":1}},"key":"AlqFFNk7v4"}],"key":"LMq1ERcI8O"}],"key":"eTbxqFN3bU"},{"type":"listItem","spread":true,"position":{"start":{"line":16,"column":1},"end":{"line":16,"column":1}},"children":[{"type":"paragraph","children":[{"type":"strong","position":{"start":{"line":16,"column":1},"end":{"line":16,"column":1}},"children":[{"type":"text","value":"I already know Python","position":{"start":{"line":16,"column":1},"end":{"line":16,"column":1}},"key":"uMtfoKhP1W"}],"key":"lNNKFNiCQI"},{"type":"text","value":" → skim 00B, then pick your data modality below.","position":{"start":{"line":16,"column":1},"end":{"line":16,"column":1}},"key":"bIUfuccdpg"}],"key":"FSwI22mb6M"}],"key":"mJIkyjIYHr"},{"type":"listItem","spread":true,"position":{"start":{"line":17,"column":1},"end":{"line":17,"column":1}},"children":[{"type":"paragraph","children":[{"type":"strong","position":{"start":{"line":17,"column":1},"end":{"line":17,"column":1}},"children":[{"type":"text","value":"I work with video","position":{"start":{"line":17,"column":1},"end":{"line":17,"column":1}},"key":"xIefiVClPZ"}],"key":"tCswx9Sdd5"},{"type":"text","value":" → ","position":{"start":{"line":17,"column":1},"end":{"line":17,"column":1}},"key":"cBxr71v3zf"},{"type":"link","url":"/module-01a-video-data","position":{"start":{"line":17,"column":1},"end":{"line":17,"column":1}},"children":[{"type":"text","value":"Module 01A · Video Data","position":{"start":{"line":17,"column":1},"end":{"line":17,"column":1}},"key":"gJmQrAdQzm"}],"urlSource":"../LS100_01A_Video-data/Module-01A_Video-Data.md","dataUrl":"/module-01a-video-data.json","internal":true,"protocol":"file","key":"bd0lUQwwoS"},{"type":"text","value":".","position":{"start":{"line":17,"column":1},"end":{"line":17,"column":1}},"key":"p8qgGenH06"}],"key":"YTLIj3Obx7"}],"key":"Cn4wFgDhKU"},{"type":"listItem","spread":true,"position":{"start":{"line":18,"column":1},"end":{"line":18,"column":1}},"children":[{"type":"paragraph","children":[{"type":"strong","position":{"start":{"line":18,"column":1},"end":{"line":18,"column":1}},"children":[{"type":"text","value":"I work with audio","position":{"start":{"line":18,"column":1},"end":{"line":18,"column":1}},"key":"fgsSek1iDK"}],"key":"yUsSFA0H3r"},{"type":"text","value":" → ","position":{"start":{"line":18,"column":1},"end":{"line":18,"column":1}},"key":"eV6FAMzG6z"},{"type":"link","url":"/module-01b-audio-data","position":{"start":{"line":18,"column":1},"end":{"line":18,"column":1}},"children":[{"type":"text","value":"Module 01B · Audio Data","position":{"start":{"line":18,"column":1},"end":{"line":18,"column":1}},"key":"dpgmH0g89y"}],"urlSource":"../LS100_01B_Audio-Data/Module-01B_Audio-Data.md","dataUrl":"/module-01b-audio-data.json","internal":true,"protocol":"file","key":"jeUqbou3XN"},{"type":"text","value":".","position":{"start":{"line":18,"column":1},"end":{"line":18,"column":1}},"key":"Z9aKhPrxEn"}],"key":"pDPAU3Ff0o"}],"key":"BQXlynTQhI"},{"type":"listItem","spread":true,"position":{"start":{"line":19,"column":1},"end":{"line":20,"column":1}},"children":[{"type":"paragraph","children":[{"type":"strong","position":{"start":{"line":19,"column":1},"end":{"line":19,"column":1}},"children":[{"type":"text","value":"I work with digital/tabular data","position":{"start":{"line":19,"column":1},"end":{"line":19,"column":1}},"key":"jw1s0W0WQg"}],"key":"TpS7ccKKoq"},{"type":"text","value":" → ","position":{"start":{"line":19,"column":1},"end":{"line":19,"column":1}},"key":"F7j3KIkuw1"},{"type":"link","url":"/module-02-data-science-and-statistics","position":{"start":{"line":19,"column":1},"end":{"line":19,"column":1}},"children":[{"type":"text","value":"Module 02 · Data Science & Statistics","position":{"start":{"line":19,"column":1},"end":{"line":19,"column":1}},"key":"chLpgX7fDd"}],"urlSource":"../LS100_02_Data-Science_Stats/Module-02_Data-Science-and-Statistics.md","dataUrl":"/module-02-data-science-and-statistics.json","internal":true,"protocol":"file","key":"w9Bajlpldl"},{"type":"text","value":".","position":{"start":{"line":19,"column":1},"end":{"line":19,"column":1}},"key":"D4Y73wKzKc"}],"key":"eIfFi0dObO"}],"key":"rFxACqjGPN"}],"key":"NwCxYgM6mE"},{"type":"heading","depth":2,"position":{"start":{"line":21,"column":1},"end":{"line":21,"column":1}},"children":[{"type":"text","value":"The milestone path","position":{"start":{"line":21,"column":1},"end":{"line":21,"column":1}},"key":"ga5yVDveGL"}],"identifier":"the-milestone-path","label":"The milestone path","html_id":"the-milestone-path","implicit":true,"key":"WyQdaQg40V"},{"type":"list","ordered":true,"start":1,"spread":false,"position":{"start":{"line":23,"column":1},"end":{"line":28,"column":1}},"children":[{"type":"listItem","spread":true,"position":{"start":{"line":23,"column":1},"end":{"line":23,"column":1}},"children":[{"type":"paragraph","children":[{"type":"strong","position":{"start":{"line":23,"column":1},"end":{"line":23,"column":1}},"children":[{"type":"text","value":"Frame your study","position":{"start":{"line":23,"column":1},"end":{"line":23,"column":1}},"key":"DDwn2MFXQ3"}],"key":"Dlc7CIX0MI"},{"type":"text","value":" — ","position":{"start":{"line":23,"column":1},"end":{"line":23,"column":1}},"key":"gMEyCZVpPb"},{"type":"link","url":"/module-00a-research-plans-and-proposals","position":{"start":{"line":23,"column":1},"end":{"line":23,"column":1}},"children":[{"type":"text","value":"Research Guide 01","position":{"start":{"line":23,"column":1},"end":{"line":23,"column":1}},"key":"z7Feg9x1EZ"}],"urlSource":"../LS100_00A_Research-Plans-And-Proposals/Module-00A_Research-Plans-And-Proposals.md","dataUrl":"/module-00a-research-plans-and-proposals.json","internal":true,"protocol":"file","key":"oHqRF3AvBv"},{"type":"text","value":": turn an interest into a researchable question.","position":{"start":{"line":23,"column":1},"end":{"line":23,"column":1}},"key":"Xfw06J70cv"}],"key":"F1k95bKb96"}],"key":"M4XRPG6xfT"},{"type":"listItem","spread":true,"position":{"start":{"line":24,"column":1},"end":{"line":24,"column":1}},"children":[{"type":"paragraph","children":[{"type":"strong","position":{"start":{"line":24,"column":1},"end":{"line":24,"column":1}},"children":[{"type":"text","value":"Build Python fluency","position":{"start":{"line":24,"column":1},"end":{"line":24,"column":1}},"key":"cGvgEixPUB"}],"key":"v30Xw6xwTH"},{"type":"text","value":" — ","position":{"start":{"line":24,"column":1},"end":{"line":24,"column":1}},"key":"X8sZ4JR48r"},{"type":"link","url":"/module-00b-python-fundamentals","position":{"start":{"line":24,"column":1},"end":{"line":24,"column":1}},"children":[{"type":"text","value":"Module 00B","position":{"start":{"line":24,"column":1},"end":{"line":24,"column":1}},"key":"aI32owU5pK"}],"urlSource":"../LS100_00B_Python-Fundamentals/Module-00B_Python-Fundamentals.md","dataUrl":"/module-00b-python-fundamentals.json","internal":true,"protocol":"file","key":"QPas4jCUZn"},{"type":"text","value":", Notebooks 01–05.","position":{"start":{"line":24,"column":1},"end":{"line":24,"column":1}},"key":"PIS5Ef0FY6"}],"key":"PBzwOfTM4h"}],"key":"SvFKC0wf0d"},{"type":"listItem","spread":true,"position":{"start":{"line":25,"column":1},"end":{"line":25,"column":1}},"children":[{"type":"paragraph","children":[{"type":"strong","position":{"start":{"line":25,"column":1},"end":{"line":25,"column":1}},"children":[{"type":"text","value":"Choose your data modality","position":{"start":{"line":25,"column":1},"end":{"line":25,"column":1}},"key":"Vplme2TkGh"}],"key":"hdDoVEu0bF"},{"type":"text","value":" — ","position":{"start":{"line":25,"column":1},"end":{"line":25,"column":1}},"key":"IUPVJ0jmcd"},{"type":"link","url":"/module-01a-video-data","position":{"start":{"line":25,"column":1},"end":{"line":25,"column":1}},"children":[{"type":"text","value":"Video (01A)","position":{"start":{"line":25,"column":1},"end":{"line":25,"column":1}},"key":"tUeJ7iCHgi"}],"urlSource":"../LS100_01A_Video-data/Module-01A_Video-Data.md","dataUrl":"/module-01a-video-data.json","internal":true,"protocol":"file","key":"pjbCU5K01S"},{"type":"text","value":" or ","position":{"start":{"line":25,"column":1},"end":{"line":25,"column":1}},"key":"QBQcom7nnV"},{"type":"link","url":"/module-01b-audio-data","position":{"start":{"line":25,"column":1},"end":{"line":25,"column":1}},"children":[{"type":"text","value":"Audio (01B)","position":{"start":{"line":25,"column":1},"end":{"line":25,"column":1}},"key":"rSJOQLS0xf"}],"urlSource":"../LS100_01B_Audio-Data/Module-01B_Audio-Data.md","dataUrl":"/module-01b-audio-data.json","internal":true,"protocol":"file","key":"TRMm2yMi7W"},{"type":"text","value":", and run the processing pipeline. ","position":{"start":{"line":25,"column":1},"end":{"line":25,"column":1}},"key":"IHPFs1Xf58"},{"type":"emphasis","position":{"start":{"line":25,"column":1},"end":{"line":25,"column":1}},"children":[{"type":"text","value":"(This is the one fork in the path — both branches rejoin at analysis.)","position":{"start":{"line":25,"column":1},"end":{"line":25,"column":1}},"key":"eAyORBndVD"}],"key":"jescADb4tm"}],"key":"z2kcotXToq"}],"key":"xBwln2x0LT"},{"type":"listItem","spread":true,"position":{"start":{"line":26,"column":1},"end":{"line":26,"column":1}},"children":[{"type":"paragraph","children":[{"type":"strong","position":{"start":{"line":26,"column":1},"end":{"line":26,"column":1}},"children":[{"type":"text","value":"Analyze your outcomes","position":{"start":{"line":26,"column":1},"end":{"line":26,"column":1}},"key":"aCQOHnP9Yr"}],"key":"A1Xa8AzdIV"},{"type":"text","value":" — ","position":{"start":{"line":26,"column":1},"end":{"line":26,"column":1}},"key":"fgbbXIJ0CQ"},{"type":"link","url":"/module-02-data-science-and-statistics","position":{"start":{"line":26,"column":1},"end":{"line":26,"column":1}},"children":[{"type":"text","value":"Module 02","position":{"start":{"line":26,"column":1},"end":{"line":26,"column":1}},"key":"MOIrut5jy3"}],"urlSource":"../LS100_02_Data-Science_Stats/Module-02_Data-Science-and-Statistics.md","dataUrl":"/module-02-data-science-and-statistics.json","internal":true,"protocol":"file","key":"DuDSNo41F8"},{"type":"text","value":", using the statistics guide and the decision-tree poster to pick the right test.","position":{"start":{"line":26,"column":1},"end":{"line":26,"column":1}},"key":"tVfF5RUO3p"}],"key":"bb0c5Du0Pl"}],"key":"a3OjpRmXAT"},{"type":"listItem","spread":true,"position":{"start":{"line":27,"column":1},"end":{"line":28,"column":1}},"children":[{"type":"paragraph","children":[{"type":"strong","position":{"start":{"line":27,"column":1},"end":{"line":27,"column":1}},"children":[{"type":"text","value":"Communicate your findings","position":{"start":{"line":27,"column":1},"end":{"line":27,"column":1}},"key":"qZ9Hb9UY2Z"}],"key":"ryRroKKgvS"},{"type":"text","value":" — ","position":{"start":{"line":27,"column":1},"end":{"line":27,"column":1}},"key":"or0I8HpEWm"},{"type":"link","url":"/module-03-communication-and-presentation","position":{"start":{"line":27,"column":1},"end":{"line":27,"column":1}},"children":[{"type":"text","value":"Research Guide 02 · Art of Communicating Science","position":{"start":{"line":27,"column":1},"end":{"line":27,"column":1}},"key":"CxtNN7o9So"}],"urlSource":"../LS100_03_Communication-and-Presentation/Module-03_Communication-and-Presentation.md","dataUrl":"/module-03-communication-and-presentation.json","internal":true,"protocol":"file","key":"iTpQ6uYApF"},{"type":"text","value":".","position":{"start":{"line":27,"column":1},"end":{"line":27,"column":1}},"key":"d86xYLDrMa"}],"key":"FFG4HoZ7zb"}],"key":"bMe7m5OkWM"}],"key":"nONRl8d4mg"},{"type":"admonition","kind":"tip","children":[{"type":"admonitionTitle","children":[{"type":"text","value":"Tip","key":"OFCfpPPiMp"}],"key":"pW1NYPrZTF"},{"type":"paragraph","position":{"start":{"line":30,"column":1},"end":{"line":31,"column":1}},"children":[{"type":"text","value":"Stuck on a term? See the ","position":{"start":{"line":30,"column":1},"end":{"line":30,"column":1}},"key":"CKKbhnmug9"},{"type":"link","url":"/module-00b-python-fundamentals","position":{"start":{"line":30,"column":1},"end":{"line":30,"column":1}},"children":[{"type":"text","value":"Essential Python Terminologies guide","position":{"start":{"line":30,"column":1},"end":{"line":30,"column":1}},"key":"CZq0OysGEn"}],"urlSource":"../LS100_00B_Python-Fundamentals/Module-00B_Python-Fundamentals.md","dataUrl":"/module-00b-python-fundamentals.json","internal":true,"protocol":"file","key":"xW97JwM4tc"},{"type":"text","value":".\nUnsure which test to use? See the ","position":{"start":{"line":30,"column":1},"end":{"line":30,"column":1}},"key":"eEGagWn3si"},{"type":"link","url":"/module-02-data-science-and-statistics","position":{"start":{"line":30,"column":1},"end":{"line":30,"column":1}},"children":[{"type":"text","value":"statistics decision tree","position":{"start":{"line":30,"column":1},"end":{"line":30,"column":1}},"key":"gPrVY4uvkO"}],"urlSource":"../LS100_02_Data-Science_Stats/Module-02_Data-Science-and-Statistics.md","dataUrl":"/module-02-data-science-and-statistics.json","internal":true,"protocol":"file","key":"SqIeNxfv8d"},{"type":"text","value":".","position":{"start":{"line":30,"column":1},"end":{"line":30,"column":1}},"key":"cTBOJJXnDj"}],"key":"EHdDqPkdej"}],"key":"L0wlDpS7Gg"}],"key":"X4cI6EJ4ev"}],"key":"eQqz1glZuW"},"references":{"cite":{"order":[],"data":{}}},"footer":{"navigation":{"prev":{"title":"LS100: Computational Behavioral Sciences","url":"/","group":"LS100: Computational Behavioral Sciences"},"next":{"title":"How to Run the Notebooks","short_title":"How to Run","url":"/how-to-run","group":"LS100: Computational Behavioral Sciences"}}},"domain":"http://localhost:3000"}